ndp/__init__.py
ndp/get_example_files.py
ndp/get_notebooks.py
ndp/reduce.py
ndp/schema.py
ndp/example_files/config.json
ndp/example_files/schema.json
ndp/jupyter/NDPReduce.ipynb
ndp/jupyter/Schema.ipynb
ndp/test/test_get.py
ndp/test/test_schema.py
ndp-0.0.2.dist-info/LICENSE
ndp-0.0.2.dist-info/METADATA
ndp-0.0.2.dist-info/WHEEL
ndp-0.0.2.dist-info/top_level.txt
ndp-0.0.2.dist-info/RECORD
