Metadata-Version: 2.1
Name: ndp
Version: 0.0.2
Summary: A python tool for reducing neutron depth profiling measurements
Author-email: Jamie Weaver <jamie.weaver@nist.gov>, Ronald Jones <ronald.jones@nist.gov>, Tyler Martin <tyler.martin@nist.gov>
License: NIST License
Project-URL: homepage, https://github.com/martintb/ndp
Project-URL: repository, https://github.com/martintb/ndp
Keywords: materials science,neutron,physics,measurement
Classifier: Development Status :: 4 - Beta
Classifier: Intended Audience :: Science/Research
Classifier: License :: Freely Distributable
Classifier: License :: Freeware
Classifier: License :: Public Domain
Classifier: Natural Language :: English
Classifier: Operating System :: MacOS
Classifier: Operating System :: Microsoft
Classifier: Operating System :: Unix
Classifier: Programming Language :: Python
Classifier: Programming Language :: Python :: 3.9
Classifier: Programming Language :: Python :: 3.10
Classifier: Programming Language :: Python :: 3.11
Classifier: Topic :: Scientific/Engineering
Classifier: Topic :: Scientific/Engineering :: Chemistry
Classifier: Topic :: Scientific/Engineering :: Physics
Requires-Python: >=3.9
License-File: LICENSE
Requires-Dist: numpy
Requires-Dist: matplotlib
Requires-Dist: jupyterlab
Provides-Extra: build
Requires-Dist: build ; extra == 'build'
Requires-Dist: twine ; extra == 'build'
Provides-Extra: test
Requires-Dist: black ; extra == 'test'
Requires-Dist: mypy ; extra == 'test'
Requires-Dist: flake8 ; extra == 'test'
Requires-Dist: pytest ; extra == 'test'
Requires-Dist: coverage ; extra == 'test'
